cppython_cmake/__init__.py
cppython_cmake/builder.py
cppython_cmake/plugin.py
cppython_cmake/py.typed
cppython_cmake/resolution.py
cppython_cmake/schema.py
cppython_cmake-0.1.1.dev18.dist-info/entry_points.txt
cppython_cmake-0.1.1.dev18.dist-info/WHEEL
cppython_cmake-0.1.1.dev18.dist-info/METADATA
cppython_cmake-0.1.1.dev18.dist-info/licenses/LICENSE.md
cppython_cmake-0.1.1.dev18.dist-info/RECORD
