Metadata-Version: 2.1
Name: cppython-cmake
Version: 0.1.1.dev18
Summary: A plugin for CPPython that enables a CMake generator for C++ projects
License: MIT
Author-email: Synodic Software <contact@synodic.software>
Requires-Python: >=3.11
Requires-Dist: cmake>=3.24.1
Requires-Dist: cppython-core>=0.3.3.dev0
Project-URL: homepage, https://github.com/Synodic-Software/CPPython-CMake
Project-URL: repository, https://github.com/Synodic-Software/CPPython-CMake
